Metadata-Version: 1.1
Name: oZip
Version: 1.1
Summary: A Simple Compression Solution
Home-page: http://oztamir.github.io/oZip/
Author: Oz Tamir
Author-email: TheOzTamir@gmail.com
License: GNU GPL v2.0
Keywords: compression zip huffman
Platform: UNKNOWN
Classifier: Development Status :: 3 - Alpha
Classifier: Topic :: System :: Archiving :: Compression
Classifier: License :: OSI Approved :: GNU General Public License v2 (GPLv2)
